jinni/__init__.py
jinni/cli.py
jinni/config_system.py
jinni/context_walker.py
jinni/core_logic.py
jinni/exceptions.py
jinni/exclusion_parser.py
jinni/file_processor.py
jinni/server.py
jinni/utils.py
mseep_jinni-0.3.0.dist-info/licenses/LICENSE
mseep_jinni-0.3.0.dist-info/METADATA
mseep_jinni-0.3.0.dist-info/WHEEL
mseep_jinni-0.3.0.dist-info/top_level.txt
mseep_jinni-0.3.0.dist-info/RECORD
